PyGraph_DFS/__init__.py
PyGraph_DFS-0.1.dist-info/LICENSE.txt
PyGraph_DFS-0.1.dist-info/METADATA
PyGraph_DFS-0.1.dist-info/WHEEL
PyGraph_DFS-0.1.dist-info/top_level.txt
PyGraph_DFS-0.1.dist-info/RECORD
