Metadata-Version: 2.1
Name: PyGraph_DFS
Version: 0.1
Summary: Implement of Depth First Search for a graph
Home-page: https://pypi.org/project/PyGraphDFS/
Author: Md. Ismiel Hossen Abir
License: MIT
License-File: LICENSE.txt
